sumonetskopecollector/__init__.py
sumonetskopecollector/netskope.py
sumonetskopecollector/netskope.yaml
sumologic_netskope_collector-1.0.10.dist-info/LICENSE
sumologic_netskope_collector-1.0.10.dist-info/METADATA
sumologic_netskope_collector-1.0.10.dist-info/WHEEL
sumologic_netskope_collector-1.0.10.dist-info/entry_points.txt
sumologic_netskope_collector-1.0.10.dist-info/top_level.txt
sumologic_netskope_collector-1.0.10.dist-info/zip-safe
sumologic_netskope_collector-1.0.10.dist-info/RECORD
