Metadata-Version: 2.1
Name: sumologic-netskope-collector
Version: 1.0.10
Summary: Sumo Logic collection solution for netskope
Home-page: https://github.com/SumoLogic/sumologic-netskope
Author: SumoLogic
Author-email: it@sumologic.com
License: PSF
Keywords: sumologic python rest api log management analytics logreduce netskope agent security siem collector forwarder
Platform: UNKNOWN
Classifier: Development Status :: 4 - Beta
Classifier: Intended Audience :: Developers
Classifier: Programming Language :: Python :: 2.7
Classifier: Programming Language :: Python :: 3.7
Classifier: Operating System :: OS Independent
Requires-Dist: sumologic-appclient-sdk (==1.0.17)
Requires-Dist: futures ; python_version < "3.2"
Requires-Dist: future-fstrings ; python_version < "3.6"
Provides-Extra: aws
Requires-Dist: boto3 (>=1.9.66) ; extra == 'aws'
Requires-Dist: botocore (>=1.12.66) ; extra == 'aws'
Provides-Extra: azure
Requires-Dist: azure-cosmosdb-table (>=1.0.5) ; extra == 'azure'
Requires-Dist: bson (>=0.5.8) ; extra == 'azure'
Provides-Extra: gcp
Requires-Dist: google-api-python-client (>=1.7.8) ; extra == 'gcp'
Requires-Dist: oauth2client (>=4.1.3) ; extra == 'gcp'
Requires-Dist: google-cloud-datastore (>=1.7.3) ; extra == 'gcp'
